{
  "YOUSIFMOD-DEVOUR_POWER.title": "Devouring",
  "YOUSIFMOD-DEVOUR_POWER.description": "Whenever you deal unblocked attack damage, heal [blue]2[/blue] HP.",
  "YOUSIFMOD-DEVOUR_POWER.smartDescription": "Whenever you deal unblocked attack damage, heal [blue]{Amount}[/blue] HP.",

  "YOUSIFMOD-DEVOUR_NO_BLOCK_POWER.title": "No Block",
  "YOUSIFMOD-DEVOUR_NO_BLOCK_POWER.description": "You cannot gain Block for this combat.",
  "YOUSIFMOD-DEVOUR_NO_BLOCK_POWER.smartDescription": "You cannot gain Block for this combat.",

  "NoBlockPower.name": "No Block",
  "NoBlockPower.description": "You cannot gain Block for this combat."
}
